letmegetcoffee.py
letmegetcoffee-0.1.0.dist-info/LICENSE
letmegetcoffee-0.1.0.dist-info/METADATA
letmegetcoffee-0.1.0.dist-info/WHEEL
letmegetcoffee-0.1.0.dist-info/top_level.txt
letmegetcoffee-0.1.0.dist-info/RECORD
