Metadata-Version: 2.1
Name: letmegetcoffee
Version: 0.1.0
Summary: Provides functionality to notify if an exception occurred
Home-page: https://github.com/RoW171/letmegetcoffee
Author: Robin 'r0w' Weiland
Author-email: robinweiland@gmx.de
License: MIT
Keywords: exception notification
Platform: UNKNOWN
Classifier: Development Status :: 4 - Beta
Classifier: Programming Language :: Python :: 3
Classifier: License :: OSI Approved :: MIT License
Classifier: Operating System :: OS Independent
Classifier: Development Status :: 4 - Beta
Classifier: Intended Audience :: Developers
Classifier: Intended Audience :: Science/Research
Classifier: Topic :: Scientific/Engineering
Requires-Python: >=3
